<annotation>
	<folder>baf1ee48-314c-46ba-8393-c646821e7d5a</folder>
	<filename>322072xlg.jpg</filename>
	<path>/Users/admin/Documents/Projects/_ML/widya_robotics_projects/week_01_day_01/baf1ee48-314c-46ba-8393-c646821e7d5a/322072xlg.jpg</path>
	<source>
		<database>Unknown</database>
	</source>
	<size>
		<width>1500</width>
		<height>1500</height>
		<depth>3</depth>
	</size>
	<segmented>0</segmented>
	<object>
		<name>ball</name>
		<pose>Unspecified</pose>
		<truncated>0</truncated>
		<difficult>0</difficult>
		<bndbox>
			<xmin>296</xmin>
			<ymin>323</ymin>
			<xmax>716</xmax>
			<ymax>752</ymax>
		</bndbox>
	</object>
	<object>
		<name>ball</name>
		<pose>Unspecified</pose>
		<truncated>0</truncated>
		<difficult>0</difficult>
		<bndbox>
			<xmin>779</xmin>
			<ymin>323</ymin>
			<xmax>1196</xmax>
			<ymax>748</ymax>
		</bndbox>
	</object>
	<object>
		<name>ball</name>
		<pose>Unspecified</pose>
		<truncated>0</truncated>
		<difficult>0</difficult>
		<bndbox>
			<xmin>291</xmin>
			<ymin>768</ymin>
			<xmax>729</xmax>
			<ymax>1193</ymax>
		</bndbox>
	</object>
	<object>
		<name>ball</name>
		<pose>Unspecified</pose>
		<truncated>0</truncated>
		<difficult>0</difficult>
		<bndbox>
			<xmin>758</xmin>
			<ymin>764</ymin>
			<xmax>1200</xmax>
			<ymax>1189</ymax>
		</bndbox>
	</object>
</annotation>
